llama_index/embeddings/ibm/__init__.py
llama_index/embeddings/ibm/base.py
llama_index/embeddings/ibm/utils.py
llama_index_embeddings_ibm-0.5.1.dist-info/METADATA
llama_index_embeddings_ibm-0.5.1.dist-info/WHEEL
llama_index_embeddings_ibm-0.5.1.dist-info/licenses/LICENSE
llama_index_embeddings_ibm-0.5.1.dist-info/RECORD
