Metadata-Version: 2.4
Name: llama-index-embeddings-ibm
Version: 0.5.1
Summary: llama-index embeddings IBM watsonx.ai integration
Author: IBM
License-Expression: MIT
License-File: LICENSE
Requires-Python: <4.0,>=3.10
Requires-Dist: ibm-watsonx-ai>=1.3.36
Requires-Dist: llama-index-core<0.15,>=0.13.0
Requires-Dist: pyarrow
